{
	"database":[
{
                        "db_engine": "postgres", 
                        "db_inst": "", 
                        "db_login": "admin", 
                        "db_password": "!Qaz2wsx3edc", 
                        "db_port": "5111", 
                        "db_server": "shc-dev-suite-jun-wan-1.hpeswlab.net", 
                        "internal": false, 
			"db_ssl": false,
                        "product_name": "sp"
                    },
                    {
                        "db_engine": "postgres",
                        "db_inst": "",   
                        "db_login": "admin",   
                        "db_password": "!Qaz2wsx3edc",
                        "db_port": "5111", 
                        "db_server": "shc-dev-suite-jun-wan-1.hpeswlab.net",
                        "internal": false, 
			"db_ssl": false,
                        "product_name": "xservices"
                    },                 
                    {
                        "db_engine": "postgres",
                        "db_inst": "",
                        "db_login": "admin",
                        "db_password": "!Qaz2wsx3edc",
                        "db_port": "5111",
                        "db_server": "shc-dev-suite-jun-wan-1.hpeswlab.net",
                        "internal": false, 
			"db_ssl": false,
                        "product_name": "idm"
                    }
	]

}
